rtl/clk_divider.v
//this is basically freq control
//it takes in a freqvalue (a 'note') and outputs a tick at the rate of that
//note
module clk_divider (
    input logic clk,
    input logic rst,
    input logic [63:0] freq_value,
    output logic tick
);

  logic [63:0] counter;

  always_ff @(posedge clk) begin
    if (rst) begin
      tick <= 0;
      counter <= 0;
    end else begin
      if (counter == freq_value) begin
        tick <= 1;
        counter <= 0;
      end else begin
        tick <= 0;
        counter <= counter + 1;
      end
    end
  end

endmodule

sim/outputs/clk_divider_wave.vcd
$version Generated by VerilatedVcd $end
$timescale 1ps $end
 $scope module TOP $end
  $var wire 1 # clk $end
  $var wire 1 $ rst $end
  $var wire 64 % freq_value [63:0] $end
  $var wire 1 ' tick $end
  $scope module clk_divider $end
   $var wire 1 # clk $end
   $var wire 1 $ rst $end
   $var wire 64 % freq_value [63:0] $end
   $var wire 1 ' tick $end
   $var wire 64 ( counter [63:0] $end
  $upscope $end
 $upscope $end
$enddefinitions $end


#0
0#
1$
b0000000000000000000000000000000000000000000000000000000110111000 %
0'
b0000000000000000000000000000000000000000000000000000000000000000 (
#10
0$
b0000000000000000000000000000000000000000000000000000000000000001 (
#20
1#
b0000000000000000000000000000000000000000000000000000000000000010 (
#30
0#
#40
1#
b0000000000000000000000000000000000000000000000000000000000000011 (
#50
0#
#60
1#
b0000000000000000000000000000000000000000000000000000000000000100 (
#70
0#
#80
1#
b0000000000000000000000000000000000000000000000000000000000000101 (
#90
0#
#100
1#
b0000000000000000000000000000000000000000000000000000000000000110 (
#110
0#
#120
1#
b0000000000000000000000000000000000000000000000000000000000000111 (
#130
0#
#140
1#
b0000000000000000000000000000000000000000000000000000000000001000 (
#150
0#
#160
1#
b0000000000000000000000000000000000000000000000000000000000001001 (
#170
0#
#180
1#
b0000000000000000000000000000000000000000000000000000000000001010 (
#190
0#
#200
1#
b0000000000000000000000000000000000000000000000000000000000001011 (
#210
0#
#220
1#
b0000000000000000000000000000000000000000000000000000000000001100 (
#230
0#
#240
1#
b0000000000000000000000000000000000000000000000000000000000001101 (
#250
0#
#260
1#
b0000000000000000000000000000000000000000000000000000000000001110 (
#270
0#
#280
1#
b0000000000000000000000000000000000000000000000000000000000001111 (
#290
0#
#300
1#
b0000000000000000000000000000000000000000000000000000000000010000 (
#310
0#
#320
1#
b0000000000000000000000000000000000000000000000000000000000010001 (
#330
0#
#340
1#
b0000000000000000000000000000000000000000000000000000000000010010 (
#350
0#
#360
1#
b0000000000000000000000000000000000000000000000000000000000010011 (
#370
0#
#380
1#
b0000000000000000000000000000000000000000000000000000000000010100 (
#390
0#
#400
1#
b0000000000000000000000000000000000000000000000000000000000010101 (
#410
0#
#420
1#
b0000000000000000000000000000000000000000000000000000000000010110 (
#430
0#
#440
1#
b0000000000000000000000000000000000000000000000000000000000010111 (
#450
0#
#460
1#
b0000000000000000000000000000000000000000000000000000000000011000 (
#470
0#
#480
1#
b0000000000000000000000000000000000000000000000000000000000011001 (
#490
0#
#500
1#
b0000000000000000000000000000000000000000000000000000000000011010 (
#510
0#
#520
1#
b0000000000000000000000000000000000000000000000000000000000011011 (
#530
0#
#540
1#
b0000000000000000000000000000000000000000000000000000000000011100 (
#550
0#
#560
1#
b0000000000000000000000000000000000000000000000000000000000011101 (
#570
0#
#580
1#
b0000000000000000000000000000000000000000000000000000000000011110 (
#590
0#
#600
1#
b0000000000000000000000000000000000000000000000000000000000011111 (
#610
0#
#620
1#
b0000000000000000000000000000000000000000000000000000000000100000 (
#630
0#
#640
1#
b0000000000000000000000000000000000000000000000000000000000100001 (
#650
0#
#660
1#
b0000000000000000000000000000000000000000000000000000000000100010 (
#670
0#
#680
1#
b0000000000000000000000000000000000000000000000000000000000100011 (
#690
0#
#700
1#
b0000000000000000000000000000000000000000000000000000000000100100 (
#710
0#
#720
1#
b0000000000000000000000000000000000000000000000000000000000100101 (
#730
0#
#740
1#
b0000000000000000000000000000000000000000000000000000000000100110 (
#750
0#
#760
1#
b0000000000000000000000000000000000000000000000000000000000100111 (
#770
0#
#780
1#
b0000000000000000000000000000000000000000000000000000000000101000 (
#790
0#
#800
1#
b0000000000000000000000000000000000000000000000000000000000101001 (
#810
0#
#820
1#
b0000000000000000000000000000000000000000000000000000000000101010 (
#830
0#
#840
1#
b0000000000000000000000000000000000000000000000000000000000101011 (
#850
0#
#860
1#
b0000000000000000000000000000000000000000000000000000000000101100 (
#870
0#
#880
1#
b0000000000000000000000000000000000000000000000000000000000101101 (
#890
0#
#900
1#
b0000000000000000000000000000000000000000000000000000000000101110 (
#910
0#
#920
1#
b0000000000000000000000000000000000000000000000000000000000101111 (
#930
0#
#940
1#
b0000000000000000000000000000000000000000000000000000000000110000 (
#950
0#
#960
1#
b0000000000000000000000000000000000000000000000000000000000110001 (
#970
0#
#980
1#
b0000000000000000000000000000000000000000000000000000000000110010 (
#990
0#
#1000
1#
b0000000000000000000000000000000000000000000000000000000000110011 (
#1010
0#
#1020
1#
b0000000000000000000000000000000000000000000000000000000000110100 (
#1030
0#
#1040
1#
b0000000000000000000000000000000000000000000000000000000000110101 (
#1050
0#
#1060
1#
b0000000000000000000000000000000000000000000000000000000000110110 (
#1070
0#
#1080
1#
b0000000000000000000000000000000000000000000000000000000000110111 (
#1090
0#
#1100
1#
b0000000000000000000000000000000000000000000000000000000000111000 (
#1110
0#
#1120
1#
b0000000000000000000000000000000000000000000000000000000000111001 (
#1130
0#
#1140
1#
b0000000000000000000000000000000000000000000000000000000000111010 (
#1150
0#
#1160
1#
b0000000000000000000000000000000000000000000000000000000000111011 (
#1170
0#
#1180
1#
b0000000000000000000000000000000000000000000000000000000000111100 (
#1190
0#
#1200
1#
b0000000000000000000000000000000000000000000000000000000000111101 (
#1210
0#
#1220
1#
b0000000000000000000000000000000000000000000000000000000000111110 (
#1230
0#
#1240
1#
b0000000000000000000000000000000000000000000000000000000000111111 (
#1250
0#
#1260
1#
b0000000000000000000000000000000000000000000000000000000001000000 (
#1270
0#
#1280
1#
b0000000000000000000000000000000000000000000000000000000001000001 (
#1290
0#
#1300
1#
b0000000000000000000000000000000000000000000000000000000001000010 (
#1310
0#
#1320
1#
b0000000000000000000000000000000000000000000000000000000001000011 (
#1330
0#
#1340
1#
b0000000000000000000000000000000000000000000000000000000001000100 (
#1350
0#
#1360
1#
b0000000000000000000000000000000000000000000000000000000001000101 (
#1370
0#
#1380
1#
b0000000000000000000000000000000000000000000000000000000001000110 (
#1390
0#
#1400
1#
b0000000000000000000000000000000000000000000000000000000001000111 (
#1410
0#
#1420
1#
b0000000000000000000000000000000000000000000000000000000001001000 (
#1430
0#
#1440
1#
b0000000000000000000000000000000000000000000000000000000001001001 (
#1450
0#
#1460
1#
b0000000000000000000000000000000000000000000000000000000001001010 (
#1470
0#
#1480
1#
b0000000000000000000000000000000000000000000000000000000001001011 (
#1490
0#
#1500
1#
b0000000000000000000000000000000000000000000000000000000001001100 (
#1510
0#
#1520
1#
b0000000000000000000000000000000000000000000000000000000001001101 (
#1530
0#
#1540
1#
b0000000000000000000000000000000000000000000000000000000001001110 (
#1550
0#
#1560
1#
b0000000000000000000000000000000000000000000000000000000001001111 (
#1570
0#
#1580
1#
b0000000000000000000000000000000000000000000000000000000001010000 (
#1590
0#
#1600
1#
b0000000000000000000000000000000000000000000000000000000001010001 (
#1610
0#
#1620
1#
b0000000000000000000000000000000000000000000000000000000001010010 (
#1630
0#
#1640
1#
b0000000000000000000000000000000000000000000000000000000001010011 (
#1650
0#
#1660
1#
b0000000000000000000000000000000000000000000000000000000001010100 (
#1670
0#
#1680
1#
b0000000000000000000000000000000000000000000000000000000001010101 (
#1690
0#
#1700
1#
b0000000000000000000000000000000000000000000000000000000001010110 (
#1710
0#
#1720
1#
b0000000000000000000000000000000000000000000000000000000001010111 (
#1730
0#
#1740
1#
b0000000000000000000000000000000000000000000000000000000001011000 (
#1750
0#
#1760
1#
b0000000000000000000000000000000000000000000000000000000001011001 (
#1770
0#
#1780
1#
b0000000000000000000000000000000000000000000000000000000001011010 (
#1790
0#
#1800
1#
b0000000000000000000000000000000000000000000000000000000001011011 (
#1810
0#
#1820
1#
b0000000000000000000000000000000000000000000000000000000001011100 (
#1830
0#
#1840
1#
b0000000000000000000000000000000000000000000000000000000001011101 (
#1850
0#
#1860
1#
b0000000000000000000000000000000000000000000000000000000001011110 (
#1870
0#
#1880
1#
b0000000000000000000000000000000000000000000000000000000001011111 (
#1890
0#
#1900
1#
b0000000000000000000000000000000000000000000000000000000001100000 (
#1910
0#
#1920
1#
b0000000000000000000000000000000000000000000000000000000001100001 (
#1930
0#
#1940
1#
b0000000000000000000000000000000000000000000000000000000001100010 (
#1950
0#
#1960
1#
b0000000000000000000000000000000000000000000000000000000001100011 (
#1970
0#
#1980
1#
b0000000000000000000000000000000000000000000000000000000001100100 (
#1990
0#
#2000
1#
b0000000000000000000000000000000000000000000000000000000001100101 (
#2010
0#
#2020
1#
b0000000000000000000000000000000000000000000000000000000001100110 (
#2030
0#
#2040
1#
b0000000000000000000000000000000000000000000000000000000001100111 (
#2050
0#
#2060
1#
b0000000000000000000000000000000000000000000000000000000001101000 (
#2070
0#
#2080
1#
b0000000000000000000000000000000000000000000000000000000001101001 (
#2090
0#
#2100
1#
b0000000000000000000000000000000000000000000000000000000001101010 (
#2110
0#
#2120
1#
b0000000000000000000000000000000000000000000000000000000001101011 (
#2130
0#
#2140
1#
b0000000000000000000000000000000000000000000000000000000001101100 (
#2150
0#
#2160
1#
b0000000000000000000000000000000000000000000000000000000001101101 (
#2170
0#
#2180
1#
b0000000000000000000000000000000000000000000000000000000001101110 (
#2190
0#
#2200
1#
b0000000000000000000000000000000000000000000000000000000001101111 (
#2210
0#
#2220
1#
b0000000000000000000000000000000000000000000000000000000001110000 (
#2230
0#
#2240
1#
b0000000000000000000000000000000000000000000000000000000001110001 (
#2250
0#
#2260
1#
b0000000000000000000000000000000000000000000000000000000001110010 (
#2270
0#
#2280
1#
b0000000000000000000000000000000000000000000000000000000001110011 (
#2290
0#
#2300
1#
b0000000000000000000000000000000000000000000000000000000001110100 (
#2310
0#
#2320
1#
b0000000000000000000000000000000000000000000000000000000001110101 (
#2330
0#
#2340
1#
b0000000000000000000000000000000000000000000000000000000001110110 (
#2350
0#
#2360
1#
b0000000000000000000000000000000000000000000000000000000001110111 (
#2370
0#
#2380
1#
b0000000000000000000000000000000000000000000000000000000001111000 (
#2390
0#
#2400
1#
b0000000000000000000000000000000000000000000000000000000001111001 (
#2410
0#
#2420
1#
b0000000000000000000000000000000000000000000000000000000001111010 (
#2430
0#
#2440
1#
b0000000000000000000000000000000000000000000000000000000001111011 (
#2450
0#
#2460
1#
b0000000000000000000000000000000000000000000000000000000001111100 (
#2470
0#
#2480
1#
b0000000000000000000000000000000000000000000000000000000001111101 (
#2490
0#
#2500
1#
b0000000000000000000000000000000000000000000000000000000001111110 (
#2510
0#
#2520
1#
b0000000000000000000000000000000000000000000000000000000001111111 (
#2530
0#
#2540
1#
b0000000000000000000000000000000000000000000000000000000010000000 (
#2550
0#
#2560
1#
b0000000000000000000000000000000000000000000000000000000010000001 (
#2570
0#
#2580
1#
b0000000000000000000000000000000000000000000000000000000010000010 (
#2590
0#
#2600
1#
b0000000000000000000000000000000000000000000000000000000010000011 (
#2610
0#
#2620
1#
b0000000000000000000000000000000000000000000000000000000010000100 (
#2630
0#
#2640
1#
b0000000000000000000000000000000000000000000000000000000010000101 (
#2650
0#
#2660
1#
b0000000000000000000000000000000000000000000000000000000010000110 (
#2670
0#
#2680
1#
b0000000000000000000000000000000000000000000000000000000010000111 (
#2690
0#
#2700
1#
b0000000000000000000000000000000000000000000000000000000010001000 (
#2710
0#
#2720
1#
b0000000000000000000000000000000000000000000000000000000010001001 (
#2730
0#
#2740
1#
b0000000000000000000000000000000000000000000000000000000010001010 (
#2750
0#
#2760
1#
b0000000000000000000000000000000000000000000000000000000010001011 (
#2770
0#
#2780
1#
b0000000000000000000000000000000000000000000000000000000010001100 (
#2790
0#
#2800
1#
b0000000000000000000000000000000000000000000000000000000010001101 (
#2810
0#
#2820
1#
b0000000000000000000000000000000000000000000000000000000010001110 (
#2830
0#
#2840
1#
b0000000000000000000000000000000000000000000000000000000010001111 (
#2850
0#
#2860
1#
b0000000000000000000000000000000000000000000000000000000010010000 (
#2870
0#
#2880
1#
b0000000000000000000000000000000000000000000000000000000010010001 (
#2890
0#
#2900
1#
b0000000000000000000000000000000000000000000000000000000010010010 (
#2910
0#
#2920
1#
b0000000000000000000000000000000000000000000000000000000010010011 (
#2930
0#
#2940
1#
b0000000000000000000000000000000000000000000000000000000010010100 (
#2950
0#
#2960
1#
b0000000000000000000000000000000000000000000000000000000010010101 (
#2970
0#
#2980
1#
b0000000000000000000000000000000000000000000000000000000010010110 (
#2990
0#
#3000
1#
b0000000000000000000000000000000000000000000000000000000010010111 (
#3010
0#
#3020
1#
b0000000000000000000000000000000000000000000000000000000010011000 (
#3030
0#
#3040
1#
b0000000000000000000000000000000000000000000000000000000010011001 (
#3050
0#
#3060
1#
b0000000000000000000000000000000000000000000000000000000010011010 (
#3070
0#
#3080
1#
b0000000000000000000000000000000000000000000000000000000010011011 (
#3090
0#
#3100
1#
b0000000000000000000000000000000000000000000000000000000010011100 (
#3110
0#
#3120
1#
b0000000000000000000000000000000000000000000000000000000010011101 (
#3130
0#
#3140
1#
b0000000000000000000000000000000000000000000000000000000010011110 (
#3150
0#
#3160
1#
b0000000000000000000000000000000000000000000000000000000010011111 (
#3170
0#
#3180
1#
b0000000000000000000000000000000000000000000000000000000010100000 (
#3190
0#
#3200
1#
b0000000000000000000000000000000000000000000000000000000010100001 (
#3210
0#
#3220
1#
b0000000000000000000000000000000000000000000000000000000010100010 (
#3230
0#
#3240
1#
b0000000000000000000000000000000000000000000000000000000010100011 (
#3250
0#
#3260
1#
b0000000000000000000000000000000000000000000000000000000010100100 (
#3270
0#
#3280
1#
b0000000000000000000000000000000000000000000000000000000010100101 (
#3290
0#
#3300
1#
b0000000000000000000000000000000000000000000000000000000010100110 (
#3310
0#
#3320
1#
b0000000000000000000000000000000000000000000000000000000010100111 (
#3330
0#
#3340
1#
b0000000000000000000000000000000000000000000000000000000010101000 (
#3350
0#
#3360
1#
b0000000000000000000000000000000000000000000000000000000010101001 (
#3370
0#
#3380
1#
b0000000000000000000000000000000000000000000000000000000010101010 (
#3390
0#
#3400
1#
b0000000000000000000000000000000000000000000000000000000010101011 (
#3410
0#
#3420
1#
b0000000000000000000000000000000000000000000000000000000010101100 (
#3430
0#
#3440
1#
b0000000000000000000000000000000000000000000000000000000010101101 (
#3450
0#
#3460
1#
b0000000000000000000000000000000000000000000000000000000010101110 (
#3470
0#
#3480
1#
b0000000000000000000000000000000000000000000000000000000010101111 (
#3490
0#
#3500
1#
b0000000000000000000000000000000000000000000000000000000010110000 (
#3510
0#
#3520
1#
b0000000000000000000000000000000000000000000000000000000010110001 (
#3530
0#
#3540
1#
b0000000000000000000000000000000000000000000000000000000010110010 (
#3550
0#
#3560
1#
b0000000000000000000000000000000000000000000000000000000010110011 (
#3570
0#
#3580
1#
b0000000000000000000000000000000000000000000000000000000010110100 (
#3590
0#
#3600
1#
b0000000000000000000000000000000000000000000000000000000010110101 (
#3610
0#
#3620
1#
b0000000000000000000000000000000000000000000000000000000010110110 (
#3630
0#
#3640
1#
b0000000000000000000000000000000000000000000000000000000010110111 (
#3650
0#
#3660
1#
b0000000000000000000000000000000000000000000000000000000010111000 (
#3670
0#
#3680
1#
b0000000000000000000000000000000000000000000000000000000010111001 (
#3690
0#
#3700
1#
b0000000000000000000000000000000000000000000000000000000010111010 (
#3710
0#
#3720
1#
b0000000000000000000000000000000000000000000000000000000010111011 (
#3730
0#
#3740
1#
b0000000000000000000000000000000000000000000000000000000010111100 (
#3750
0#
#3760
1#
b0000000000000000000000000000000000000000000000000000000010111101 (
#3770
0#
#3780
1#
b0000000000000000000000000000000000000000000000000000000010111110 (
#3790
0#
#3800
1#
b0000000000000000000000000000000000000000000000000000000010111111 (
#3810
0#
#3820
1#
b0000000000000000000000000000000000000000000000000000000011000000 (
#3830
0#
#3840
1#
b0000000000000000000000000000000000000000000000000000000011000001 (
#3850
0#
#3860
1#
b0000000000000000000000000000000000000000000000000000000011000010 (
#3870
0#
#3880
1#
b0000000000000000000000000000000000000000000000000000000011000011 (
#3890
0#
#3900
1#
b0000000000000000000000000000000000000000000000000000000011000100 (
#3910
0#
#3920
1#
b0000000000000000000000000000000000000000000000000000000011000101 (
#3930
0#
#3940
1#
b0000000000000000000000000000000000000000000000000000000011000110 (
#3950
0#
#3960
1#
b0000000000000000000000000000000000000000000000000000000011000111 (
#3970
0#
#3980
1#
b0000000000000000000000000000000000000000000000000000000011001000 (
#3990
0#
#4000
1#
b0000000000000000000000000000000000000000000000000000000011001001 (
#4010
0#
#4020
1#
b0000000000000000000000000000000000000000000000000000000011001010 (
#4030
0#
#4040
1#
b0000000000000000000000000000000000000000000000000000000011001011 (
#4050
0#
#4060
1#
b0000000000000000000000000000000000000000000000000000000011001100 (
#4070
0#
#4080
1#
b0000000000000000000000000000000000000000000000000000000011001101 (
#4090
0#
#4100
1#
b0000000000000000000000000000000000000000000000000000000011001110 (
#4110
0#
#4120
1#
b0000000000000000000000000000000000000000000000000000000011001111 (
#4130
0#
#4140
1#
b0000000000000000000000000000000000000000000000000000000011010000 (
#4150
0#
#4160
1#
b0000000000000000000000000000000000000000000000000000000011010001 (
#4170
0#
#4180
1#
b0000000000000000000000000000000000000000000000000000000011010010 (
#4190
0#
#4200
1#
b0000000000000000000000000000000000000000000000000000000011010011 (
#4210
0#
#4220
1#
b0000000000000000000000000000000000000000000000000000000011010100 (
#4230
0#
#4240
1#
b0000000000000000000000000000000000000000000000000000000011010101 (
#4250
0#
#4260
1#
b0000000000000000000000000000000000000000000000000000000011010110 (
#4270
0#
#4280
1#
b0000000000000000000000000000000000000000000000000000000011010111 (
#4290
0#
#4300
1#
b0000000000000000000000000000000000000000000000000000000011011000 (
#4310
0#
#4320
1#
b0000000000000000000000000000000000000000000000000000000011011001 (
#4330
0#
#4340
1#
b0000000000000000000000000000000000000000000000000000000011011010 (
#4350
0#
#4360
1#
b0000000000000000000000000000000000000000000000000000000011011011 (
#4370
0#
#4380
1#
b0000000000000000000000000000000000000000000000000000000011011100 (
#4390
0#
#4400
1#
b0000000000000000000000000000000000000000000000000000000011011101 (
#4410
0#
#4420
1#
b0000000000000000000000000000000000000000000000000000000011011110 (
#4430
0#
#4440
1#
b0000000000000000000000000000000000000000000000000000000011011111 (
#4450
0#
#4460
1#
b0000000000000000000000000000000000000000000000000000000011100000 (
#4470
0#
#4480
1#
b0000000000000000000000000000000000000000000000000000000011100001 (
#4490
0#
#4500
1#
b0000000000000000000000000000000000000000000000000000000011100010 (
#4510
0#
#4520
1#
b0000000000000000000000000000000000000000000000000000000011100011 (
#4530
0#
#4540
1#
b0000000000000000000000000000000000000000000000000000000011100100 (
#4550
0#
#4560
1#
b0000000000000000000000000000000000000000000000000000000011100101 (
#4570
0#
#4580
1#
b0000000000000000000000000000000000000000000000000000000011100110 (
#4590
0#
#4600
1#
b0000000000000000000000000000000000000000000000000000000011100111 (
#4610
0#
#4620
1#
b0000000000000000000000000000000000000000000000000000000011101000 (
#4630
0#
#4640
1#
b0000000000000000000000000000000000000000000000000000000011101001 (
#4650
0#
#4660
1#
b0000000000000000000000000000000000000000000000000000000011101010 (
#4670
0#
#4680
1#
b0000000000000000000000000000000000000000000000000000000011101011 (
#4690
0#
#4700
1#
b0000000000000000000000000000000000000000000000000000000011101100 (
#4710
0#
#4720
1#
b0000000000000000000000000000000000000000000000000000000011101101 (
#4730
0#
#4740
1#
b0000000000000000000000000000000000000000000000000000000011101110 (
#4750
0#
#4760
1#
b0000000000000000000000000000000000000000000000000000000011101111 (
#4770
0#
#4780
1#
b0000000000000000000000000000000000000000000000000000000011110000 (
#4790
0#
#4800
1#
b0000000000000000000000000000000000000000000000000000000011110001 (
#4810
0#
#4820
1#
b0000000000000000000000000000000000000000000000000000000011110010 (
#4830
0#
#4840
1#
b0000000000000000000000000000000000000000000000000000000011110011 (
#4850
0#
#4860
1#
b0000000000000000000000000000000000000000000000000000000011110100 (
#4870
0#
#4880
1#
b0000000000000000000000000000000000000000000000000000000011110101 (
#4890
0#
#4900
1#
b0000000000000000000000000000000000000000000000000000000011110110 (
#4910
0#
#4920
1#
b0000000000000000000000000000000000000000000000000000000011110111 (
#4930
0#
#4940
1#
b0000000000000000000000000000000000000000000000000000000011111000 (
#4950
0#
#4960
1#
b0000000000000000000000000000000000000000000000000000000011111001 (
#4970
0#
#4980
1#
b0000000000000000000000000000000000000000000000000000000011111010 (
#4990
0#
#5000
1#
b0000000000000000000000000000000000000000000000000000000011111011 (
#5010
0#
#5020
1#
b0000000000000000000000000000000000000000000000000000000011111100 (
#5030
0#
#5040
1#
b0000000000000000000000000000000000000000000000000000000011111101 (
#5050
0#
#5060
1#
b0000000000000000000000000000000000000000000000000000000011111110 (
#5070
0#
#5080
1#
b0000000000000000000000000000000000000000000000000000000011111111 (
#5090
0#
#5100
1#
b0000000000000000000000000000000000000000000000000000000100000000 (
#5110
0#
#5120
1#
b0000000000000000000000000000000000000000000000000000000100000001 (
#5130
0#
#5140
1#
b0000000000000000000000000000000000000000000000000000000100000010 (
#5150
0#
#5160
1#
b0000000000000000000000000000000000000000000000000000000100000011 (
#5170
0#
#5180
1#
b0000000000000000000000000000000000000000000000000000000100000100 (
#5190
0#
#5200
1#
b0000000000000000000000000000000000000000000000000000000100000101 (
#5210
0#
#5220
1#
b0000000000000000000000000000000000000000000000000000000100000110 (
#5230
0#
#5240
1#
b0000000000000000000000000000000000000000000000000000000100000111 (
#5250
0#
#5260
1#
b0000000000000000000000000000000000000000000000000000000100001000 (
#5270
0#
#5280
1#
b0000000000000000000000000000000000000000000000000000000100001001 (
#5290
0#
#5300
1#
b0000000000000000000000000000000000000000000000000000000100001010 (
#5310
0#
#5320
1#
b0000000000000000000000000000000000000000000000000000000100001011 (
#5330
0#
#5340
1#
b0000000000000000000000000000000000000000000000000000000100001100 (
#5350
0#
#5360
1#
b0000000000000000000000000000000000000000000000000000000100001101 (
#5370
0#
#5380
1#
b0000000000000000000000000000000000000000000000000000000100001110 (
#5390
0#
#5400
1#
b0000000000000000000000000000000000000000000000000000000100001111 (
#5410
0#
#5420
1#
b0000000000000000000000000000000000000000000000000000000100010000 (
#5430
0#
#5440
1#
b0000000000000000000000000000000000000000000000000000000100010001 (
#5450
0#
#5460
1#
b0000000000000000000000000000000000000000000000000000000100010010 (
#5470
0#
#5480
1#
b0000000000000000000000000000000000000000000000000000000100010011 (
#5490
0#
#5500
1#
b0000000000000000000000000000000000000000000000000000000100010100 (
#5510
0#
#5520
1#
b0000000000000000000000000000000000000000000000000000000100010101 (
#5530
0#
#5540
1#
b0000000000000000000000000000000000000000000000000000000100010110 (
#5550
0#
#5560
1#
b0000000000000000000000000000000000000000000000000000000100010111 (
#5570
0#
#5580
1#
b0000000000000000000000000000000000000000000000000000000100011000 (
#5590
0#
#5600
1#
b0000000000000000000000000000000000000000000000000000000100011001 (
#5610
0#
#5620
1#
b0000000000000000000000000000000000000000000000000000000100011010 (
#5630
0#
#5640
1#
b0000000000000000000000000000000000000000000000000000000100011011 (
#5650
0#
#5660
1#
b0000000000000000000000000000000000000000000000000000000100011100 (
#5670
0#
#5680
1#
b0000000000000000000000000000000000000000000000000000000100011101 (
#5690
0#
#5700
1#
b0000000000000000000000000000000000000000000000000000000100011110 (
#5710
0#
#5720
1#
b0000000000000000000000000000000000000000000000000000000100011111 (
#5730
0#
#5740
1#
b0000000000000000000000000000000000000000000000000000000100100000 (
#5750
0#
#5760
1#
b0000000000000000000000000000000000000000000000000000000100100001 (
#5770
0#
#5780
1#
b0000000000000000000000000000000000000000000000000000000100100010 (
#5790
0#
#5800
1#
b0000000000000000000000000000000000000000000000000000000100100011 (
#5810
0#
#5820
1#
b0000000000000000000000000000000000000000000000000000000100100100 (
#5830
0#
#5840
1#
b0000000000000000000000000000000000000000000000000000000100100101 (
#5850
0#
#5860
1#
b0000000000000000000000000000000000000000000000000000000100100110 (
#5870
0#
#5880
1#
b0000000000000000000000000000000000000000000000000000000100100111 (
#5890
0#
#5900
1#
b0000000000000000000000000000000000000000000000000000000100101000 (
#5910
0#
#5920
1#
b0000000000000000000000000000000000000000000000000000000100101001 (
#5930
0#
#5940
1#
b0000000000000000000000000000000000000000000000000000000100101010 (
#5950
0#
#5960
1#
b0000000000000000000000000000000000000000000000000000000100101011 (
#5970
0#
#5980
1#
b0000000000000000000000000000000000000000000000000000000100101100 (
#5990
0#
#6000
1#
b0000000000000000000000000000000000000000000000000000000100101101 (
#6010
0#
#6020
1#
b0000000000000000000000000000000000000000000000000000000100101110 (
#6030
0#
#6040
1#
b0000000000000000000000000000000000000000000000000000000100101111 (
#6050
0#
#6060
1#
b0000000000000000000000000000000000000000000000000000000100110000 (
#6070
0#
#6080
1#
b0000000000000000000000000000000000000000000000000000000100110001 (
#6090
0#
#6100
1#
b0000000000000000000000000000000000000000000000000000000100110010 (
#6110
0#
#6120
1#
b0000000000000000000000000000000000000000000000000000000100110011 (
#6130
0#
#6140
1#
b0000000000000000000000000000000000000000000000000000000100110100 (
#6150
0#
#6160
1#
b0000000000000000000000000000000000000000000000000000000100110101 (
#6170
0#
#6180
1#
b0000000000000000000000000000000000000000000000000000000100110110 (
#6190
0#
#6200
1#
b0000000000000000000000000000000000000000000000000000000100110111 (
#6210
0#
#6220
1#
b0000000000000000000000000000000000000000000000000000000100111000 (
#6230
0#
#6240
1#
b0000000000000000000000000000000000000000000000000000000100111001 (
#6250
0#
#6260
1#
b0000000000000000000000000000000000000000000000000000000100111010 (
#6270
0#
#6280
1#
b0000000000000000000000000000000000000000000000000000000100111011 (
#6290
0#
#6300
1#
b0000000000000000000000000000000000000000000000000000000100111100 (
#6310
0#
#6320
1#
b0000000000000000000000000000000000000000000000000000000100111101 (
#6330
0#
#6340
1#
b0000000000000000000000000000000000000000000000000000000100111110 (
#6350
0#
#6360
1#
b0000000000000000000000000000000000000000000000000000000100111111 (
#6370
0#
#6380
1#
b0000000000000000000000000000000000000000000000000000000101000000 (
#6390
0#
#6400
1#
b0000000000000000000000000000000000000000000000000000000101000001 (
#6410
0#
#6420
1#
b0000000000000000000000000000000000000000000000000000000101000010 (
#6430
0#
#6440
1#
b0000000000000000000000000000000000000000000000000000000101000011 (
#6450
0#
#6460
1#
b0000000000000000000000000000000000000000000000000000000101000100 (
#6470
0#
#6480
1#
b0000000000000000000000000000000000000000000000000000000101000101 (
#6490
0#
#6500
1#
b0000000000000000000000000000000000000000000000000000000101000110 (
#6510
0#
#6520
1#
b0000000000000000000000000000000000000000000000000000000101000111 (
#6530
0#
#6540
1#
b0000000000000000000000000000000000000000000000000000000101001000 (
#6550
0#
#6560
1#
b0000000000000000000000000000000000000000000000000000000101001001 (
#6570
0#
#6580
1#
b0000000000000000000000000000000000000000000000000000000101001010 (
#6590
0#
#6600
1#
b0000000000000000000000000000000000000000000000000000000101001011 (
#6610
0#
#6620
1#
b0000000000000000000000000000000000000000000000000000000101001100 (
#6630
0#
#6640
1#
b0000000000000000000000000000000000000000000000000000000101001101 (
#6650
0#
#6660
1#
b0000000000000000000000000000000000000000000000000000000101001110 (
#6670
0#
#6680
1#
b0000000000000000000000000000000000000000000000000000000101001111 (
#6690
0#
#6700
1#
b0000000000000000000000000000000000000000000000000000000101010000 (
#6710
0#
#6720
1#
b0000000000000000000000000000000000000000000000000000000101010001 (
#6730
0#
#6740
1#
b0000000000000000000000000000000000000000000000000000000101010010 (
#6750
0#
#6760
1#
b0000000000000000000000000000000000000000000000000000000101010011 (
#6770
0#
#6780
1#
b0000000000000000000000000000000000000000000000000000000101010100 (
#6790
0#
#6800
1#
b0000000000000000000000000000000000000000000000000000000101010101 (
#6810
0#
#6820
1#
b0000000000000000000000000000000000000000000000000000000101010110 (
#6830
0#
#6840
1#
b0000000000000000000000000000000000000000000000000000000101010111 (
#6850
0#
#6860
1#
b0000000000000000000000000000000000000000000000000000000101011000 (
#6870
0#
#6880
1#
b0000000000000000000000000000000000000000000000000000000101011001 (
#6890
0#
#6900
1#
b0000000000000000000000000000000000000000000000000000000101011010 (
#6910
0#
#6920
1#
b0000000000000000000000000000000000000000000000000000000101011011 (
#6930
0#
#6940
1#
b0000000000000000000000000000000000000000000000000000000101011100 (
#6950
0#
#6960
1#
b0000000000000000000000000000000000000000000000000000000101011101 (
#6970
0#
#6980
1#
b0000000000000000000000000000000000000000000000000000000101011110 (
#6990
0#
#7000
1#
b0000000000000000000000000000000000000000000000000000000101011111 (
#7010
0#
#7020
1#
b0000000000000000000000000000000000000000000000000000000101100000 (
#7030
0#
#7040
1#
b0000000000000000000000000000000000000000000000000000000101100001 (
#7050
0#
#7060
1#
b0000000000000000000000000000000000000000000000000000000101100010 (
#7070
0#
#7080
1#
b0000000000000000000000000000000000000000000000000000000101100011 (
#7090
0#
#7100
1#
b0000000000000000000000000000000000000000000000000000000101100100 (
#7110
0#
#7120
1#
b0000000000000000000000000000000000000000000000000000000101100101 (
#7130
0#
#7140
1#
b0000000000000000000000000000000000000000000000000000000101100110 (
#7150
0#
#7160
1#
b0000000000000000000000000000000000000000000000000000000101100111 (
#7170
0#
#7180
1#
b0000000000000000000000000000000000000000000000000000000101101000 (
#7190
0#
#7200
1#
b0000000000000000000000000000000000000000000000000000000101101001 (
#7210
0#
#7220
1#
b0000000000000000000000000000000000000000000000000000000101101010 (
#7230
0#
#7240
1#
b0000000000000000000000000000000000000000000000000000000101101011 (
#7250
0#
#7260
1#
b0000000000000000000000000000000000000000000000000000000101101100 (
