rtl/osc_square.v
module osc_square (
    input logic clk,
    input logic rst,
    input logic enable,
    input logic [31:0] phase_inc,
    output logic wave_out
);

    logic [31:0] phase;

    always_ff @(posedge clk) begin
        if (rst) begin
            phase <= 0;
            wave_out <= 0;
        end else if (enable) begin
            phase <= phase + phase_inc;
            wave_out <= phase[31];  // MSB is square wave
        end
    end
endmodule

sim/outputs/osc_square_wave.vcd
$version Generated by VerilatedVcd $end
$timescale 1ps $end
 $scope module TOP $end
  $var wire 1 # clk $end
  $var wire 1 $ rst $end
  $var wire 1 % enable $end
  $var wire 32 & phase_inc [31:0] $end
  $var wire 1 ' wave_out $end
  $scope module osc_square $end
   $var wire 1 # clk $end
   $var wire 1 $ rst $end
   $var wire 1 % enable $end
   $var wire 32 & phase_inc [31:0] $end
   $var wire 1 ' wave_out $end
   $var wire 32 ( phase [31:0] $end
  $upscope $end
 $upscope $end
$enddefinitions $end


#0
0#
1$
0%
b00000000000000000000000000000000 &
0'
b00000000000000000000000000000000 (
#10
0$
1%
b00000010010110001011111100100101 &
b00000010010110001011111100100101 (
#20
1#
b00000100101100010111111001001010 (
#30
0#
#40
1#
b00000111000010100011110101101111 (
#50
0#
#60
1#
b00001001011000101111110010010100 (
#70
0#
#80
1#
b00001011101110111011101110111001 (
#90
0#
#100
1#
b00001110000101000111101011011110 (
#110
0#
#120
1#
b00010000011011010011101000000011 (
#130
0#
#140
1#
b00010010110001011111100100101000 (
#150
0#
#160
1#
b00010101000111101011100001001101 (
#170
0#
#180
1#
b00010111011101110111011101110010 (
#190
0#
#200
1#
b00011001110100000011011010010111 (
#210
0#
#220
1#
b00011100001010001111010110111100 (
#230
0#
#240
1#
b00011110100000011011010011100001 (
#250
0#
#260
1#
b00100000110110100111010000000110 (
#270
0#
#280
1#
b00100011001100110011001100101011 (
#290
0#
#300
1#
b00100101100010111111001001010000 (
#310
0#
#320
1#
b00100111111001001011000101110101 (
#330
0#
#340
1#
b00101010001111010111000010011010 (
#350
0#
#360
1#
b00101100100101100010111110111111 (
#370
0#
#380
1#
b00101110111011101110111011100100 (
#390
0#
#400
1#
b00110001010001111010111000001001 (
#410
0#
#420
1#
b00110011101000000110110100101110 (
#430
0#
#440
1#
b00110101111110010010110001010011 (
#450
0#
#460
1#
b00111000010100011110101101111000 (
#470
0#
#480
1#
b00111010101010101010101010011101 (
#490
0#
#500
1#
b00111101000000110110100111000010 (
#510
0#
#520
1#
b00111111010111000010100011100111 (
#530
0#
#540
1#
b01000001101101001110100000001100 (
#550
0#
#560
1#
b01000100000011011010011100110001 (
#570
0#
#580
1#
b01000110011001100110011001010110 (
#590
0#
#600
1#
b01001000101111110010010101111011 (
#610
0#
#620
1#
b01001011000101111110010010100000 (
#630
0#
#640
1#
b01001101011100001010001111000101 (
#650
0#
#660
1#
b01001111110010010110001011101010 (
#670
0#
#680
1#
b01010010001000100010001000001111 (
#690
0#
#700
1#
b01010100011110101110000100110100 (
#710
0#
#720
1#
b01010110110100111010000001011001 (
#730
0#
#740
1#
b01011001001011000101111101111110 (
#750
0#
#760
1#
b01011011100001010001111010100011 (
#770
0#
#780
1#
b01011101110111011101110111001000 (
#790
0#
#800
1#
b01100000001101101001110011101101 (
#810
0#
#820
1#
b01100010100011110101110000010010 (
#830
0#
#840
1#
b01100100111010000001101100110111 (
#850
0#
#860
1#
b01100111010000001101101001011100 (
#870
0#
#880
1#
b01101001100110011001100110000001 (
#890
0#
#900
1#
b01101011111100100101100010100110 (
#910
0#
#920
1#
b01101110010010110001011111001011 (
#930
0#
#940
1#
b01110000101000111101011011110000 (
#950
0#
#960
1#
b01110010111111001001011000010101 (
#970
0#
#980
1#
b01110101010101010101010100111010 (
#990
0#
#1000
1#
b01110111101011100001010001011111 (
#1010
0#
#1020
1#
b01111010000001101101001110000100 (
#1030
0#
#1040
1#
b01111100010111111001001010101001 (
#1050
0#
#1060
1#
b01111110101110000101000111001110 (
#1070
0#
#1080
1#
b10000001000100010001000011110011 (
#1090
0#
#1100
1#
1'
b10000011011010011101000000011000 (
#1110
0#
#1120
1#
b10000101110000101000111100111101 (
#1130
0#
#1140
1#
b10001000000110110100111001100010 (
#1150
0#
#1160
1#
b10001010011101000000110110000111 (
#1170
0#
#1180
1#
b10001100110011001100110010101100 (
#1190
0#
#1200
1#
b10001111001001011000101111010001 (
#1210
0#
#1220
1#
b10010001011111100100101011110110 (
#1230
0#
#1240
1#
b10010011110101110000101000011011 (
#1250
0#
#1260
1#
b10010110001011111100100101000000 (
#1270
0#
#1280
1#
b10011000100010001000100001100101 (
#1290
0#
#1300
1#
b10011010111000010100011110001010 (
#1310
0#
#1320
1#
b10011101001110100000011010101111 (
#1330
0#
#1340
1#
b10011111100100101100010111010100 (
#1350
0#
#1360
1#
b10100001111010111000010011111001 (
#1370
0#
#1380
1#
b10100100010001000100010000011110 (
#1390
0#
#1400
1#
b10100110100111010000001101000011 (
#1410
0#
#1420
1#
b10101000111101011100001001101000 (
#1430
0#
#1440
1#
b10101011010011101000000110001101 (
#1450
0#
#1460
1#
b10101101101001110100000010110010 (
#1470
0#
#1480
1#
b10101111111111111111111111010111 (
#1490
0#
#1500
1#
b10110010010110001011111011111100 (
#1510
0#
#1520
1#
b10110100101100010111111000100001 (
#1530
0#
#1540
1#
b10110111000010100011110101000110 (
#1550
0#
#1560
1#
b10111001011000101111110001101011 (
#1570
0#
#1580
1#
b10111011101110111011101110010000 (
#1590
0#
#1600
1#
b10111110000101000111101010110101 (
#1610
0#
#1620
1#
b11000000011011010011100111011010 (
#1630
0#
#1640
1#
b11000010110001011111100011111111 (
#1650
0#
#1660
1#
b11000101000111101011100000100100 (
#1670
0#
#1680
1#
b11000111011101110111011101001001 (
#1690
0#
#1700
1#
b11001001110100000011011001101110 (
#1710
0#
#1720
1#
b11001100001010001111010110010011 (
#1730
0#
#1740
1#
b11001110100000011011010010111000 (
#1750
0#
#1760
1#
b11010000110110100111001111011101 (
#1770
0#
#1780
1#
b11010011001100110011001100000010 (
#1790
0#
#1800
1#
b11010101100010111111001000100111 (
#1810
0#
#1820
1#
b11010111111001001011000101001100 (
#1830
0#
#1840
1#
b11011010001111010111000001110001 (
#1850
0#
#1860
1#
b11011100100101100010111110010110 (
#1870
0#
#1880
1#
b11011110111011101110111010111011 (
#1890
0#
#1900
1#
b11100001010001111010110111100000 (
#1910
0#
#1920
1#
b11100011101000000110110100000101 (
#1930
0#
#1940
1#
b11100101111110010010110000101010 (
#1950
0#
#1960
1#
b11101000010100011110101101001111 (
#1970
0#
#1980
1#
b11101010101010101010101001110100 (
#1990
0#
#2000
1#
b11101101000000110110100110011001 (
#2010
0#
#2020
1#
b11101111010111000010100010111110 (
#2030
0#
#2040
1#
b11110001101101001110011111100011 (
#2050
0#
#2060
1#
b11110100000011011010011100001000 (
#2070
0#
#2080
1#
b11110110011001100110011000101101 (
#2090
0#
#2100
1#
b11111000101111110010010101010010 (
#2110
0#
#2120
1#
b11111011000101111110010001110111 (
#2130
0#
#2140
1#
b11111101011100001010001110011100 (
#2150
0#
#2160
1#
b11111111110010010110001011000001 (
#2170
0#
#2180
1#
b00000010001000100010000111100110 (
#2190
0#
#2200
1#
0'
b00000100011110101110000100001011 (
#2210
0#
#2220
1#
b00000110110100111010000000110000 (
#2230
0#
#2240
1#
b00001001001011000101111101010101 (
#2250
0#
#2260
1#
b00001011100001010001111001111010 (
#2270
0#
#2280
1#
b00001101110111011101110110011111 (
#2290
0#
#2300
1#
b00010000001101101001110011000100 (
#2310
0#
#2320
1#
b00010010100011110101101111101001 (
#2330
0#
#2340
1#
b00010100111010000001101100001110 (
#2350
0#
#2360
1#
b00010111010000001101101000110011 (
#2370
0#
#2380
1#
b00011001100110011001100101011000 (
#2390
0#
#2400
1#
b00011011111100100101100001111101 (
#2410
0#
#2420
1#
b00011110010010110001011110100010 (
#2430
0#
#2440
1#
b00100000101000111101011011000111 (
#2450
0#
#2460
1#
b00100010111111001001010111101100 (
#2470
0#
#2480
1#
b00100101010101010101010100010001 (
#2490
0#
#2500
1#
b00100111101011100001010000110110 (
#2510
0#
#2520
1#
b00101010000001101101001101011011 (
#2530
0#
#2540
1#
b00101100010111111001001010000000 (
#2550
0#
#2560
1#
b00101110101110000101000110100101 (
#2570
0#
#2580
1#
b00110001000100010001000011001010 (
#2590
0#
#2600
1#
b00110011011010011100111111101111 (
#2610
0#
#2620
1#
b00110101110000101000111100010100 (
#2630
0#
#2640
1#
b00111000000110110100111000111001 (
#2650
0#
#2660
1#
b00111010011101000000110101011110 (
#2670
0#
#2680
1#
b00111100110011001100110010000011 (
#2690
0#
#2700
1#
b00111111001001011000101110101000 (
#2710
0#
#2720
1#
b01000001011111100100101011001101 (
#2730
0#
#2740
1#
b01000011110101110000100111110010 (
#2750
0#
#2760
1#
b01000110001011111100100100010111 (
#2770
0#
#2780
1#
b01001000100010001000100000111100 (
#2790
0#
#2800
1#
b01001010111000010100011101100001 (
#2810
0#
#2820
1#
b01001101001110100000011010000110 (
#2830
0#
#2840
1#
b01001111100100101100010110101011 (
#2850
0#
#2860
1#
b01010001111010111000010011010000 (
#2870
0#
#2880
1#
b01010100010001000100001111110101 (
#2890
0#
#2900
1#
b01010110100111010000001100011010 (
#2910
0#
#2920
1#
b01011000111101011100001000111111 (
#2930
0#
#2940
1#
b01011011010011101000000101100100 (
#2950
0#
#2960
1#
b01011101101001110100000010001001 (
#2970
0#
#2980
1#
b01011111111111111111111110101110 (
#2990
0#
#3000
1#
b01100010010110001011111011010011 (
#3010
0#
#3020
1#
b01100100101100010111110111111000 (
#3030
0#
#3040
1#
b01100111000010100011110100011101 (
#3050
0#
#3060
1#
b01101001011000101111110001000010 (
#3070
0#
#3080
1#
b01101011101110111011101101100111 (
#3090
0#
#3100
1#
b01101110000101000111101010001100 (
#3110
0#
#3120
1#
b01110000011011010011100110110001 (
#3130
0#
#3140
1#
b01110010110001011111100011010110 (
#3150
0#
#3160
1#
b01110101000111101011011111111011 (
#3170
0#
#3180
1#
b01110111011101110111011100100000 (
#3190
0#
#3200
1#
b01111001110100000011011001000101 (
#3210
0#
#3220
1#
b01111100001010001111010101101010 (
#3230
0#
#3240
1#
b01111110100000011011010010001111 (
#3250
0#
#3260
1#
b10000000110110100111001110110100 (
#3270
0#
#3280
1#
1'
b10000011001100110011001011011001 (
#3290
0#
#3300
1#
b10000101100010111111000111111110 (
#3310
0#
#3320
1#
b10000111111001001011000100100011 (
#3330
0#
#3340
1#
b10001010001111010111000001001000 (
#3350
0#
#3360
1#
b10001100100101100010111101101101 (
#3370
0#
#3380
1#
b10001110111011101110111010010010 (
#3390
0#
#3400
1#
b10010001010001111010110110110111 (
#3410
0#
#3420
1#
b10010011101000000110110011011100 (
#3430
0#
#3440
1#
b10010101111110010010110000000001 (
#3450
0#
#3460
1#
b10011000010100011110101100100110 (
#3470
0#
#3480
1#
b10011010101010101010101001001011 (
#3490
0#
#3500
1#
b10011101000000110110100101110000 (
#3510
0#
#3520
1#
b10011111010111000010100010010101 (
#3530
0#
#3540
1#
b10100001101101001110011110111010 (
#3550
0#
#3560
1#
b10100100000011011010011011011111 (
#3570
0#
#3580
1#
b10100110011001100110011000000100 (
#3590
0#
#3600
1#
b10101000101111110010010100101001 (
#3610
0#
#3620
1#
b10101011000101111110010001001110 (
#3630
0#
#3640
1#
b10101101011100001010001101110011 (
#3650
0#
#3660
1#
b10101111110010010110001010011000 (
#3670
0#
#3680
1#
b10110010001000100010000110111101 (
#3690
0#
#3700
1#
b10110100011110101110000011100010 (
#3710
0#
#3720
1#
b10110110110100111010000000000111 (
#3730
0#
#3740
1#
b10111001001011000101111100101100 (
#3750
0#
#3760
1#
b10111011100001010001111001010001 (
#3770
0#
#3780
1#
b10111101110111011101110101110110 (
#3790
0#
#3800
1#
b11000000001101101001110010011011 (
#3810
0#
#3820
1#
b11000010100011110101101111000000 (
#3830
0#
#3840
1#
b11000100111010000001101011100101 (
#3850
0#
#3860
1#
b11000111010000001101101000001010 (
#3870
0#
#3880
1#
b11001001100110011001100100101111 (
#3890
0#
#3900
1#
b11001011111100100101100001010100 (
#3910
0#
#3920
1#
b11001110010010110001011101111001 (
#3930
0#
#3940
1#
b11010000101000111101011010011110 (
#3950
0#
#3960
1#
b11010010111111001001010111000011 (
#3970
0#
#3980
1#
b11010101010101010101010011101000 (
#3990
0#
#4000
1#
b11010111101011100001010000001101 (
#4010
0#
#4020
1#
b11011010000001101101001100110010 (
#4030
0#
#4040
1#
b11011100010111111001001001010111 (
#4050
0#
#4060
1#
b11011110101110000101000101111100 (
#4070
0#
#4080
1#
b11100001000100010001000010100001 (
#4090
0#
#4100
1#
b11100011011010011100111111000110 (
#4110
0#
#4120
1#
b11100101110000101000111011101011 (
#4130
0#
#4140
1#
b11101000000110110100111000010000 (
#4150
0#
#4160
1#
b11101010011101000000110100110101 (
#4170
0#
#4180
1#
b11101100110011001100110001011010 (
#4190
0#
#4200
1#
b11101111001001011000101101111111 (
#4210
0#
#4220
1#
b11110001011111100100101010100100 (
#4230
0#
#4240
1#
b11110011110101110000100111001001 (
#4250
0#
#4260
1#
b11110110001011111100100011101110 (
#4270
0#
#4280
1#
b11111000100010001000100000010011 (
#4290
0#
#4300
1#
b11111010111000010100011100111000 (
#4310
0#
#4320
1#
b11111101001110100000011001011101 (
#4330
0#
#4340
1#
b11111111100100101100010110000010 (
#4350
0#
#4360
1#
b00000001111010111000010010100111 (
#4370
0#
#4380
1#
0'
b00000100010001000100001111001100 (
#4390
0#
#4400
1#
b00000110100111010000001011110001 (
#4410
0#
#4420
1#
b00001000111101011100001000010110 (
#4430
0#
#4440
1#
b00001011010011101000000100111011 (
#4450
0#
#4460
1#
b00001101101001110100000001100000 (
#4470
0#
#4480
1#
b00001111111111111111111110000101 (
#4490
0#
#4500
1#
b00010010010110001011111010101010 (
#4510
0#
#4520
1#
b00010100101100010111110111001111 (
#4530
0#
#4540
1#
b00010111000010100011110011110100 (
#4550
0#
#4560
1#
b00011001011000101111110000011001 (
#4570
0#
#4580
1#
b00011011101110111011101100111110 (
#4590
0#
#4600
1#
b00011110000101000111101001100011 (
#4610
0#
#4620
1#
b00100000011011010011100110001000 (
#4630
0#
#4640
1#
b00100010110001011111100010101101 (
#4650
0#
#4660
1#
b00100101000111101011011111010010 (
#4670
0#
#4680
1#
b00100111011101110111011011110111 (
#4690
0#
#4700
1#
b00101001110100000011011000011100 (
#4710
0#
#4720
1#
b00101100001010001111010101000001 (
#4730
0#
#4740
1#
b00101110100000011011010001100110 (
#4750
0#
#4760
1#
b00110000110110100111001110001011 (
#4770
0#
#4780
1#
b00110011001100110011001010110000 (
#4790
0#
#4800
1#
b00110101100010111111000111010101 (
#4810
0#
#4820
1#
b00110111111001001011000011111010 (
#4830
0#
#4840
1#
b00111010001111010111000000011111 (
#4850
0#
#4860
1#
b00111100100101100010111101000100 (
#4870
0#
#4880
1#
b00111110111011101110111001101001 (
#4890
0#
#4900
1#
b01000001010001111010110110001110 (
#4910
0#
#4920
1#
b01000011101000000110110010110011 (
#4930
0#
#4940
1#
b01000101111110010010101111011000 (
#4950
0#
#4960
1#
b01001000010100011110101011111101 (
#4970
0#
#4980
1#
b01001010101010101010101000100010 (
#4990
0#
#5000
1#
b01001101000000110110100101000111 (
#5010
0#
#5020
1#
b01001111010111000010100001101100 (
#5030
0#
#5040
1#
b01010001101101001110011110010001 (
#5050
0#
#5060
1#
b01010100000011011010011010110110 (
#5070
0#
#5080
1#
b01010110011001100110010111011011 (
#5090
0#
#5100
1#
b01011000101111110010010100000000 (
#5110
0#
#5120
1#
b01011011000101111110010000100101 (
#5130
0#
#5140
1#
b01011101011100001010001101001010 (
#5150
0#
#5160
1#
b01011111110010010110001001101111 (
#5170
0#
#5180
1#
b01100010001000100010000110010100 (
#5190
0#
#5200
1#
b01100100011110101110000010111001 (
#5210
0#
#5220
1#
b01100110110100111001111111011110 (
#5230
0#
#5240
1#
b01101001001011000101111100000011 (
#5250
0#
#5260
1#
b01101011100001010001111000101000 (
#5270
0#
#5280
1#
b01101101110111011101110101001101 (
#5290
0#
#5300
1#
b01110000001101101001110001110010 (
#5310
0#
#5320
1#
b01110010100011110101101110010111 (
#5330
0#
#5340
1#
b01110100111010000001101010111100 (
#5350
0#
#5360
1#
b01110111010000001101100111100001 (
#5370
0#
#5380
1#
b01111001100110011001100100000110 (
#5390
0#
#5400
1#
b01111011111100100101100000101011 (
#5410
0#
#5420
1#
b01111110010010110001011101010000 (
#5430
0#
#5440
1#
b10000000101000111101011001110101 (
#5450
0#
#5460
1#
1'
b10000010111111001001010110011010 (
#5470
0#
#5480
1#
b10000101010101010101010010111111 (
#5490
0#
#5500
1#
b10000111101011100001001111100100 (
#5510
0#
#5520
1#
b10001010000001101101001100001001 (
#5530
0#
#5540
1#
b10001100010111111001001000101110 (
#5550
0#
#5560
1#
b10001110101110000101000101010011 (
#5570
0#
#5580
1#
b10010001000100010001000001111000 (
#5590
0#
#5600
1#
b10010011011010011100111110011101 (
#5610
0#
#5620
1#
b10010101110000101000111011000010 (
#5630
0#
#5640
1#
b10011000000110110100110111100111 (
#5650
0#
#5660
1#
b10011010011101000000110100001100 (
#5670
0#
#5680
1#
b10011100110011001100110000110001 (
#5690
0#
#5700
1#
b10011111001001011000101101010110 (
#5710
0#
#5720
1#
b10100001011111100100101001111011 (
#5730
0#
#5740
1#
b10100011110101110000100110100000 (
#5750
0#
#5760
1#
b10100110001011111100100011000101 (
#5770
0#
#5780
1#
b10101000100010001000011111101010 (
#5790
0#
#5800
1#
b10101010111000010100011100001111 (
#5810
0#
#5820
1#
b10101101001110100000011000110100 (
#5830
0#
#5840
1#
b10101111100100101100010101011001 (
#5850
0#
#5860
1#
b10110001111010111000010001111110 (
#5870
0#
#5880
1#
b10110100010001000100001110100011 (
#5890
0#
#5900
1#
b10110110100111010000001011001000 (
#5910
0#
#5920
1#
b10111000111101011100000111101101 (
#5930
0#
#5940
1#
b10111011010011101000000100010010 (
#5950
0#
#5960
1#
b10111101101001110100000000110111 (
#5970
0#
#5980
1#
b10111111111111111111111101011100 (
#5990
0#
#6000
1#
b11000010010110001011111010000001 (
#6010
0#
#6020
1#
b11000100101100010111110110100110 (
#6030
0#
#6040
1#
b11000111000010100011110011001011 (
#6050
0#
#6060
1#
b11001001011000101111101111110000 (
#6070
0#
#6080
1#
b11001011101110111011101100010101 (
#6090
0#
#6100
1#
b11001110000101000111101000111010 (
#6110
0#
#6120
1#
b11010000011011010011100101011111 (
#6130
0#
#6140
1#
b11010010110001011111100010000100 (
#6150
0#
#6160
1#
b11010101000111101011011110101001 (
#6170
0#
#6180
1#
b11010111011101110111011011001110 (
#6190
0#
#6200
1#
b11011001110100000011010111110011 (
#6210
0#
#6220
1#
b11011100001010001111010100011000 (
#6230
0#
#6240
1#
b11011110100000011011010000111101 (
#6250
0#
#6260
1#
b11100000110110100111001101100010 (
#6270
0#
#6280
1#
b11100011001100110011001010000111 (
#6290
0#
#6300
1#
b11100101100010111111000110101100 (
#6310
0#
#6320
1#
b11100111111001001011000011010001 (
#6330
0#
#6340
1#
b11101010001111010110111111110110 (
#6350
0#
#6360
1#
b11101100100101100010111100011011 (
#6370
0#
#6380
1#
b11101110111011101110111001000000 (
#6390
0#
#6400
1#
b11110001010001111010110101100101 (
#6410
0#
#6420
1#
b11110011101000000110110010001010 (
#6430
0#
#6440
1#
b11110101111110010010101110101111 (
#6450
0#
#6460
1#
b11111000010100011110101011010100 (
#6470
0#
#6480
1#
b11111010101010101010100111111001 (
#6490
0#
#6500
1#
b11111101000000110110100100011110 (
#6510
0#
#6520
1#
b11111111010111000010100001000011 (
#6530
0#
#6540
1#
b00000001101101001110011101101000 (
#6550
0#
#6560
1#
0'
b00000100000011011010011010001101 (
#6570
0#
#6580
1#
b00000110011001100110010110110010 (
#6590
0#
#6600
1#
b00001000101111110010010011010111 (
#6610
0#
#6620
1#
b00001011000101111110001111111100 (
#6630
0#
#6640
1#
b00001101011100001010001100100001 (
#6650
0#
#6660
1#
b00001111110010010110001001000110 (
#6670
0#
#6680
1#
b00010010001000100010000101101011 (
#6690
0#
#6700
1#
b00010100011110101110000010010000 (
#6710
0#
#6720
1#
b00010110110100111001111110110101 (
#6730
0#
#6740
1#
b00011001001011000101111011011010 (
#6750
0#
#6760
1#
b00011011100001010001110111111111 (
#6770
0#
#6780
1#
b00011101110111011101110100100100 (
#6790
0#
#6800
1#
b00100000001101101001110001001001 (
#6810
0#
#6820
1#
b00100010100011110101101101101110 (
#6830
0#
#6840
1#
b00100100111010000001101010010011 (
#6850
0#
#6860
1#
b00100111010000001101100110111000 (
#6870
0#
#6880
1#
b00101001100110011001100011011101 (
#6890
0#
#6900
1#
b00101011111100100101100000000010 (
#6910
0#
#6920
1#
b00101110010010110001011100100111 (
#6930
0#
#6940
1#
b00110000101000111101011001001100 (
#6950
0#
#6960
1#
b00110010111111001001010101110001 (
#6970
0#
#6980
1#
b00110101010101010101010010010110 (
#6990
0#
#7000
1#
b00110111101011100001001110111011 (
#7010
0#
#7020
1#
b00111010000001101101001011100000 (
#7030
0#
#7040
1#
b00111100010111111001001000000101 (
#7050
0#
#7060
1#
b00111110101110000101000100101010 (
#7070
0#
#7080
1#
b01000001000100010001000001001111 (
#7090
0#
#7100
1#
b01000011011010011100111101110100 (
#7110
0#
#7120
1#
b01000101110000101000111010011001 (
#7130
0#
#7140
1#
b01001000000110110100110110111110 (
#7150
0#
#7160
1#
b01001010011101000000110011100011 (
#7170
0#
#7180
1#
b01001100110011001100110000001000 (
#7190
0#
#7200
1#
b01001111001001011000101100101101 (
#7210
0#
#7220
1#
b01010001011111100100101001010010 (
#7230
0#
#7240
1#
b01010011110101110000100101110111 (
#7250
0#
#7260
1#
b01010110001011111100100010011100 (
#7270
0#
#7280
1#
b01011000100010001000011111000001 (
#7290
0#
#7300
1#
b01011010111000010100011011100110 (
#7310
0#
#7320
1#
b01011101001110100000011000001011 (
#7330
0#
#7340
1#
b01011111100100101100010100110000 (
#7350
0#
#7360
1#
b01100001111010111000010001010101 (
#7370
0#
#7380
1#
b01100100010001000100001101111010 (
#7390
0#
#7400
1#
b01100110100111010000001010011111 (
#7410
0#
#7420
1#
b01101000111101011100000111000100 (
#7430
0#
#7440
1#
b01101011010011101000000011101001 (
#7450
0#
#7460
1#
b01101101101001110100000000001110 (
#7470
0#
#7480
1#
b01101111111111111111111100110011 (
#7490
0#
#7500
1#
b01110010010110001011111001011000 (
#7510
0#
#7520
1#
b01110100101100010111110101111101 (
#7530
0#
#7540
1#
b01110111000010100011110010100010 (
#7550
0#
#7560
1#
b01111001011000101111101111000111 (
#7570
0#
#7580
1#
b01111011101110111011101011101100 (
#7590
0#
#7600
1#
b01111110000101000111101000010001 (
#7610
0#
#7620
1#
b10000000011011010011100100110110 (
#7630
0#
#7640
1#
1'
b10000010110001011111100001011011 (
#7650
0#
#7660
1#
b10000101000111101011011110000000 (
#7670
0#
#7680
1#
b10000111011101110111011010100101 (
#7690
0#
#7700
1#
b10001001110100000011010111001010 (
#7710
0#
#7720
1#
b10001100001010001111010011101111 (
#7730
0#
#7740
1#
b10001110100000011011010000010100 (
#7750
0#
#7760
1#
b10010000110110100111001100111001 (
#7770
0#
#7780
1#
b10010011001100110011001001011110 (
#7790
0#
#7800
1#
b10010101100010111111000110000011 (
#7810
0#
#7820
1#
b10010111111001001011000010101000 (
#7830
0#
#7840
1#
b10011010001111010110111111001101 (
#7850
0#
#7860
1#
b10011100100101100010111011110010 (
#7870
0#
#7880
1#
b10011110111011101110111000010111 (
#7890
0#
#7900
1#
b10100001010001111010110100111100 (
#7910
0#
#7920
1#
b10100011101000000110110001100001 (
#7930
0#
#7940
1#
b10100101111110010010101110000110 (
#7950
0#
#7960
1#
b10101000010100011110101010101011 (
#7970
0#
#7980
1#
b10101010101010101010100111010000 (
#7990
0#
#8000
1#
b10101101000000110110100011110101 (
#8010
0#
#8020
1#
b10101111010111000010100000011010 (
#8030
0#
#8040
1#
b10110001101101001110011100111111 (
#8050
0#
#8060
1#
b10110100000011011010011001100100 (
#8070
0#
#8080
1#
b10110110011001100110010110001001 (
#8090
0#
#8100
1#
b10111000101111110010010010101110 (
#8110
0#
#8120
1#
b10111011000101111110001111010011 (
#8130
0#
#8140
1#
b10111101011100001010001011111000 (
#8150
0#
#8160
1#
b10111111110010010110001000011101 (
#8170
0#
#8180
1#
b11000010001000100010000101000010 (
#8190
0#
#8200
1#
b11000100011110101110000001100111 (
#8210
0#
#8220
1#
b11000110110100111001111110001100 (
#8230
0#
#8240
1#
b11001001001011000101111010110001 (
#8250
0#
#8260
1#
b11001011100001010001110111010110 (
#8270
0#
#8280
1#
b11001101110111011101110011111011 (
#8290
0#
#8300
1#
b11010000001101101001110000100000 (
#8310
0#
#8320
1#
b11010010100011110101101101000101 (
#8330
0#
#8340
1#
b11010100111010000001101001101010 (
#8350
0#
#8360
1#
b11010111010000001101100110001111 (
#8370
0#
#8380
1#
b11011001100110011001100010110100 (
#8390
0#
#8400
1#
b11011011111100100101011111011001 (
#8410
0#
#8420
1#
b11011110010010110001011011111110 (
#8430
0#
#8440
1#
b11100000101000111101011000100011 (
#8450
0#
#8460
1#
b11100010111111001001010101001000 (
#8470
0#
#8480
1#
b11100101010101010101010001101101 (
#8490
0#
#8500
1#
b11100111101011100001001110010010 (
#8510
0#
#8520
1#
b11101010000001101101001010110111 (
#8530
0#
#8540
1#
b11101100010111111001000111011100 (
#8550
0#
#8560
1#
b11101110101110000101000100000001 (
#8570
0#
#8580
1#
b11110001000100010001000000100110 (
#8590
0#
#8600
1#
b11110011011010011100111101001011 (
#8610
0#
#8620
1#
b11110101110000101000111001110000 (
#8630
0#
#8640
1#
b11111000000110110100110110010101 (
#8650
0#
#8660
1#
b11111010011101000000110010111010 (
#8670
0#
#8680
1#
b11111100110011001100101111011111 (
#8690
0#
#8700
1#
b11111111001001011000101100000100 (
#8710
0#
#8720
1#
b00000001011111100100101000101001 (
#8730
0#
#8740
1#
0'
b00000011110101110000100101001110 (
#8750
0#
#8760
1#
b00000110001011111100100001110011 (
#8770
0#
#8780
1#
b00001000100010001000011110011000 (
#8790
0#
#8800
1#
b00001010111000010100011010111101 (
#8810
0#
#8820
1#
b00001101001110100000010111100010 (
#8830
0#
#8840
1#
b00001111100100101100010100000111 (
#8850
0#
#8860
1#
b00010001111010111000010000101100 (
#8870
0#
#8880
1#
b00010100010001000100001101010001 (
#8890
0#
#8900
1#
b00010110100111010000001001110110 (
#8910
0#
#8920
1#
b00011000111101011100000110011011 (
#8930
0#
#8940
1#
b00011011010011101000000011000000 (
#8950
0#
#8960
1#
b00011101101001110011111111100101 (
#8970
0#
#8980
1#
b00011111111111111111111100001010 (
#8990
0#
#9000
1#
b00100010010110001011111000101111 (
#9010
0#
#9020
1#
b00100100101100010111110101010100 (
#9030
0#
#9040
1#
b00100111000010100011110001111001 (
#9050
0#
#9060
1#
b00101001011000101111101110011110 (
#9070
0#
#9080
1#
b00101011101110111011101011000011 (
#9090
0#
#9100
1#
b00101110000101000111100111101000 (
#9110
0#
#9120
1#
b00110000011011010011100100001101 (
#9130
0#
#9140
1#
b00110010110001011111100000110010 (
#9150
0#
#9160
1#
b00110101000111101011011101010111 (
#9170
0#
#9180
1#
b00110111011101110111011001111100 (
#9190
0#
#9200
1#
b00111001110100000011010110100001 (
#9210
0#
#9220
1#
b00111100001010001111010011000110 (
#9230
0#
#9240
1#
b00111110100000011011001111101011 (
#9250
0#
#9260
1#
b01000000110110100111001100010000 (
#9270
0#
#9280
1#
b01000011001100110011001000110101 (
#9290
0#
#9300
1#
b01000101100010111111000101011010 (
#9310
0#
#9320
1#
b01000111111001001011000001111111 (
#9330
0#
#9340
1#
b01001010001111010110111110100100 (
#9350
0#
#9360
1#
b01001100100101100010111011001001 (
#9370
0#
#9380
1#
b01001110111011101110110111101110 (
#9390
0#
#9400
1#
b01010001010001111010110100010011 (
#9410
0#
#9420
1#
b01010011101000000110110000111000 (
#9430
0#
#9440
1#
b01010101111110010010101101011101 (
#9450
0#
#9460
1#
b01011000010100011110101010000010 (
#9470
0#
#9480
1#
b01011010101010101010100110100111 (
#9490
0#
#9500
1#
b01011101000000110110100011001100 (
#9510
0#
#9520
1#
b01011111010111000010011111110001 (
#9530
0#
#9540
1#
b01100001101101001110011100010110 (
#9550
0#
#9560
1#
b01100100000011011010011000111011 (
#9570
0#
#9580
1#
b01100110011001100110010101100000 (
#9590
0#
#9600
1#
b01101000101111110010010010000101 (
#9610
0#
#9620
1#
b01101011000101111110001110101010 (
#9630
0#
#9640
1#
b01101101011100001010001011001111 (
#9650
0#
#9660
1#
b01101111110010010110000111110100 (
#9670
0#
#9680
1#
b01110010001000100010000100011001 (
#9690
0#
#9700
1#
b01110100011110101110000000111110 (
#9710
0#
#9720
1#
b01110110110100111001111101100011 (
#9730
0#
#9740
1#
b01111001001011000101111010001000 (
#9750
0#
#9760
1#
b01111011100001010001110110101101 (
#9770
0#
#9780
1#
b01111101110111011101110011010010 (
#9790
0#
#9800
1#
b10000000001101101001101111110111 (
#9810
0#
#9820
1#
1'
b10000010100011110101101100011100 (
#9830
0#
#9840
1#
b10000100111010000001101001000001 (
#9850
0#
#9860
1#
b10000111010000001101100101100110 (
#9870
0#
#9880
1#
b10001001100110011001100010001011 (
#9890
0#
#9900
1#
b10001011111100100101011110110000 (
#9910
0#
#9920
1#
b10001110010010110001011011010101 (
#9930
0#
#9940
1#
b10010000101000111101010111111010 (
#9950
0#
#9960
1#
b10010010111111001001010100011111 (
#9970
0#
#9980
1#
b10010101010101010101010001000100 (
#9990
0#
#10000
1#
b10010111101011100001001101101001 (
#10010
0#
#10020
1#
b10011010000001101101001010001110 (
